{
  "append_only_baseline": "harder_one_shot_with_audit_checklist",
  "conditions": [
    "event_loop_scheduled",
    "append_only"
  ],
  "declared_loss_policy": "exact_marker_contract_required",
  "experiment_id": "harder_append_only_baseline_20260618",
  "live_model_calls": true,
  "non_inferiority_margin": 0.1,
  "symbolic_contract": "framework_bound_symbolic_continuation.v1",
  "tasks": [
    "declared_loss_discipline",
    "identity_drift_boundary",
    "multi_wake_continuation",
    "ordinary_synthesis",
    "restart_frontier_reconstruction"
  ]
}
